[{"val":1074.5,"perc":2.01,"sel_perc":2},{"val":947.76,"perc":4,"sel_perc":4},{"val":863.63,"perc":6,"sel_perc":6},{"val":807.77,"perc":7.99,"sel_perc":8},{"val":764.46,"perc":10,"sel_perc":10},{"val":728.36,"perc":12.01,"sel_perc":12},{"val":697.68,"perc":14,"sel_perc":14},{"val":670.16,"perc":16,"sel_perc":16},{"val":645.12,"perc":17.99,"sel_perc":18},{"val":621.64,"perc":20,"sel_perc":20},{"val":599.25,"perc":22.01,"sel_perc":22},{"val":577.67,"perc":24,"sel_perc":24},{"val":556.73,"perc":26,"sel_perc":26},{"val":536.9,"perc":27.99,"sel_perc":28},{"val":517.86,"perc":30,"sel_perc":30},{"val":499.82,"perc":32.01,"sel_perc":32},{"val":482.8,"perc":34,"sel_perc":34},{"val":466.61,"perc":36,"sel_perc":36},{"val":451.31,"perc":37.99,"sel_perc":38},{"val":436.57,"perc":40,"sel_perc":40},{"val":422.52,"perc":42.01,"sel_perc":42},{"val":409.21,"perc":44,"sel_perc":44},{"val":396.5,"perc":46,"sel_perc":46},{"val":384.58,"perc":47.99,"sel_perc":48},{"val":373.21,"perc":50,"sel_perc":50},{"val":362.47,"perc":52.01,"sel_perc":52},{"val":352.36,"perc":54,"sel_perc":54},{"val":342.69,"perc":56,"sel_perc":56},{"val":333.6,"perc":57.99,"sel_perc":58},{"val":324.89,"perc":60,"sel_perc":60},{"val":316.59,"perc":62.01,"sel_perc":62},{"val":308.73,"perc":64,"sel_perc":64},{"val":301.18,"perc":66,"sel_perc":66},{"val":294.05,"perc":67.99,"sel_perc":68},{"val":287.19,"perc":70,"sel_perc":70},{"val":280.64,"perc":72.01,"sel_perc":72},{"val":274.41,"perc":74,"sel_perc":74},{"val":268.4,"perc":76,"sel_perc":76},{"val":262.67,"perc":77.99,"sel_perc":78},{"val":257.13,"perc":80,"sel_perc":80},{"val":251.79,"perc":82.01,"sel_perc":82},{"val":246.7,"perc":84,"sel_perc":84},{"val":241.77,"perc":86,"sel_perc":86},{"val":237.06,"perc":87.99,"sel_perc":88},{"val":232.47,"perc":90,"sel_perc":90},{"val":228.05,"perc":92.01,"sel_perc":92},{"val":223.8,"perc":94,"sel_perc":94},{"val":219.64,"perc":96,"sel_perc":96},{"val":215.62,"perc":97.99,"sel_perc":98},{"val":211.67,"perc":100,"sel_perc":100}]